[
    {
        "date": "2026-06-05",
        "category": "行政",
        "source": "教務處",
        "title": "114學年度第2學期第3次定期考範圍及考程表",
        "url": "https://www.cmjh.tn.edu.tw/modules/school/index.php?department_id=2&zone_id=0&page_id=12&content_id=325&type=news&from_op=all_news",
        "content": "臺南市立崇明國民中學114學年度第二學期第三次定期考考試範圍\n科目\n一年級考試範圍\n二年級考試範圍\n國文\nL7〜L10、成語第六回\nL7〜L10、自學(一)、成語突破12\n英語\nL5〜Review 3+書寫體\nL4〜Review 3\n數學\n3-2〜L6\n3-4〜4-3\n生物\n3-5實驗〜5-2 (P96〜P187)\n理化\nL5〜L6\n歷史\nL5〜L6\nL5〜L6\n地理\nL5〜L6\nL5〜L6\n公民\nL5〜L6\nL5〜L6\n臺南市立崇明國民中學114學年度第二學期第三次定期考考試日程表\n日期\n6月25日(四)\n6月26日(五)\n一年級\n二年級\n一年級\n二年級\n第一節\n自修（8：20～9：00）40min\n自修（8：20～8：45）25min\n第二節\n自修（9：10～9：50）40min\n國文（9：00～10：00）(60分鐘)\n第三節\n自修（10：00～10：35）35min\n自修（10：10～10：35）25min\n第四節\n社會（10：50～11：50）(60分鐘)\n英文 (10：50～11：50）(60分鐘)\n午餐及午休\n第五節\n自修（13：25～13：55）30min\n自修（13：25～13：55）30min\n第六節\n自修（14：05～14：40）35min\n自修（14：05～14：40）35min\n第七節\n數學（14：55～15：55）(60分鐘)\n自然（14：55～15：55）(60分鐘)",
        "attachments": [
            {
                "name": "114-2-3 考試範圍及考試日程表.pdf",
                "link": "https://www.cmjh.tn.edu.tw/modules/school/index.php?op=tufdl&fn=114-2-3 考試範圍及考試日程表.pdf&files_sn=232"
            }
        ]
    },
    {
        "date": "2026-06-04",
        "category": "升學",
        "source": "輔導室",
        "title": "應屆畢業生「會考成績查詢」與「升學進路調查」",
        "url": "https://www.cmjh.tn.edu.tw/modules/school/index.php?department_id=5&zone_id=0&page_id=39&content_id=323&type=news&from_op=all_news",
        "content": "【應屆畢業生會考成績查詢與升學進路調查】\n🌟國中教育會考成績查詢\n自6月5日(五)上午8點以後，可透過以下網頁查詢：\n國中教育會考官網\n國中教育會考全國試務會\n查詢帳號為會考「准考證號」，密碼為「身分證字號後4碼」。\n※會考個人紙本成績單預計在當天中午前發至各班給同學。\n🌟畢業後關鍵時程表：\n（請設定鬧鐘提醒）\n日 期\n階 段\n重要提醒\n6/18(四)～6/23(二)\n選填志願\n臺南區高級中等學校免試入學系統\n開放志願選填及查詢個人序位區間。\n6/24(三)～6/25(四)\n返校簽名\n【重要】回崇明國中確認志願單。\n同學與家長親自簽名，請勿遠遊。\n7/7(二)前\n錄取公告\n各升學管道將陸續放榜，請密切留意公告。\n7/9(四)\n高中職報到\n若本人無法親自報到，可委託家長代理。\n（請先洽詢錄取學校確認）\n給親愛的國三同學們：\n透過練習選填志願，你正在養成個人生涯發展的關鍵能力——\n■自我評估　　■決策考量　　■資訊運用　　■承擔結果\n輔導室提醒你：\n1.會考成績確認後，與家長討論是否調整志願序。\n2.排好順序再填志願，每一志願序填滿３所學校。\n3.留意志願選填及報到日程，確認就讀學校後，請務必填寫\n「\n畢業生升學進路回報表單\n」\n。\n🌟重要：每個人都要填，若逾期未回報，教育局將會持續追蹤，務求掌握全體畢業生動向。\n沒有絕對正確的選擇，只有努力把選擇變得正確。\n勇敢地填下你想去的方向，然後帶著這份勇氣去迎接新的生活。\n加油，未來的風景一定比現在想像的更精彩！",
        "attachments": []
    },
    {
        "date": "2026-06-03",
        "category": "一般",
        "source": "教務處",
        "title": "115學年度新生雙語適性社團錄取及備取名單",
        "url": "https://www.cmjh.tn.edu.tw/modules/school/index.php?department_id=2&zone_id=0&page_id=12&content_id=315&type=news&from_op=all_news",
        "content": "一、115學年度新生雙語適性社團錄取及備取名單如附件，請自行下載查閱。\n二、有關學生個人成績單，後續將個別通知，特此說明。",
        "attachments": [
            {
                "name": "115新生雙語適性社錄取及備取名單_核章版(1).pdf",
                "link": "https://www.cmjh.tn.edu.tw/modules/school/index.php?op=tufdl&fn=115新生雙語適性社錄取及備取名單_核章版(1).pdf&files_sn=221"
            }
        ]
    },
    {
        "date": "2026-06-03",
        "category": "活動",
        "source": "學務處",
        "title": "臺南市立崇明國中第 33 屆畢業典禮程序表及注意事項",
        "url": "https://www.cmjh.tn.edu.tw/modules/school/index.php?department_id=3&zone_id=0&page_id=21&content_id=294&type=news&from_op=all_news",
        "content": "",
        "attachments": []
    },
    {
        "date": "2026-05-26",
        "category": "一般",
        "source": "教務處",
        "title": "[在校生] 115學年度各年級教科書用書版本",
        "url": "https://www.cmjh.tn.edu.tw/modules/school/index.php?department_id=2&zone_id=0&page_id=12&content_id=242&type=news&from_op=all_news",
        "content": "一二三年級使用版本\n請見附件",
        "attachments": [
            {
                "name": "臺南市崇明國中115學年度各年級教科書用書版本.pdf",
                "link": "https://www.cmjh.tn.edu.tw/modules/school/index.php?op=tufdl&fn=臺南市崇明國中115學年度各年級教科書用書版本.pdf&files_sn=173"
            }
        ]
    },
    {
        "date": "2026-06-08",
        "category": "活動",
        "source": "輔導室",
        "title": "敬邀家長參與臺南大學附屬高級中學辦理之「技職特色宣導說明會」",
        "url": "https://www.cmjh.tn.edu.tw/modules/school/index.php?department_id=5&zone_id=0&page_id=39&content_id=327&type=news&from_op=all_news",
        "content": "主旨：敬邀家長參與臺南大學附屬高級中學辦理之「技職特色宣導說明會」，請查照。\n說明：\n一、依據114學年度高職優質化輔助方案子計畫:「114-3-3辦理國中學生家長之技職特色宣導」辦理。\n二、辦理日期:115年06月15日(星期一)、06月17日(星期三)\n三、辦理時間:晚上6:30~8:00\n四、辦理地點:南大附中敬業樓一樓K書中心(教務處旁)\n五、報名連結：\n技職特色宣導說明會報名系統",
        "attachments": [
            {
                "name": "南大附中.pdf",
                "link": "https://www.cmjh.tn.edu.tw/modules/school/index.php?op=tufdl&fn=南大附中.pdf&files_sn=234"
            }
        ]
    },
    {
        "date": "2026-06-08",
        "category": "升學",
        "source": "輔導室",
        "title": "臺南二中「高一新生實驗班招生甄選說明會」（線上）",
        "url": "https://www.cmjh.tn.edu.tw/modules/school/index.php?department_id=5&zone_id=0&page_id=39&content_id=326&type=news&from_op=all_news",
        "content": "臺南二中「115學年度高一新生實驗班招生甄選說明會」\n說明：\n一、依據國教署核定本校115學年度3個實驗班計畫辦理。\n二、參加對象：臺南區各國中師長、家長、學生等對本校實驗班課程有興趣者。\n三、說明會時間：115年06月10日（星期三） 18:30~20:00。\n四、說明會地點（線上辦理）：GoogleMeet（會議室代碼：hfc-qdmi-bau）\n五、說明會內容：本校3個實驗班（巴斯德生醫、圖靈電資、雙語）介紹、實驗班入班方式、Q&A。\n六、本次說明會海報詳如附件。",
        "attachments": []
    },
    {
        "date": "2026-06-05",
        "category": "宣導",
        "source": "輔導室",
        "title": "臺南市家庭教育中心委託欣橋心理治療所辦理「單身育兒不孤單」個別輔導計畫",
        "url": "https://www.cmjh.tn.edu.tw/modules/school/index.php?department_id=5&zone_id=0&page_id=39&content_id=324&type=news&from_op=all_news",
        "content": "說明：\n一、旨揭計畫係為服務符合優先接受家庭教育服務之單親、已離婚登記或實際單獨照顧未成年子女者，及經評估家庭功能較薄弱且有心理支持需求，並育有未成年子女者，提供諮商服務及辦理家庭教育講座活動，若貴單位服務對象有此需求之個案，請協助轉知及轉介。\n二、為避免資源重疊使用，若本（115）年度已有使用本中心「創造心生活，帶愛向前走」個別輔導計畫之個案，請勿重複申請。",
        "attachments": [
            {
                "name": "單身育兒個別輔導計畫.pdf",
                "link": "https://www.cmjh.tn.edu.tw/modules/school/index.php?op=tufdl&fn=單身育兒個別輔導計畫.pdf&files_sn=231"
            }
        ]
    },
    {
        "date": "2026-06-04",
        "category": "研習",
        "source": "教務處",
        "title": "本市114學年度本土語文教師藝文場館參訪計畫，歡迎本土語教支人員踴躍報名參加。",
        "url": "https://www.cmjh.tn.edu.tw/modules/school/index.php?department_id=2&zone_id=0&page_id=12&content_id=322&type=news&from_op=all_news",
        "content": "一、依據本市114學年度本土教育整體推動方案辦理。\n二、活動時間：115年7月10日(星期五)。\n三、活動地點：七股潟湖及隆田chacha文化資產教育園區。\n四、參加對象：本市本土語文輔導團員及本市本土語文(閩語、客語、原民語)教學支援工作人員。\n五、實施方式：\n(一)七股潟湖參訪。\n(二)隆田chacha文化資產教育園區參訪。\n(三)教師社群交流座談。\n六、報名方式：\n(一)報名自即日起至6月18日(星期四)，錄取共70人，依報名順序錄取。錄取人員將個別通知，請務必留下正確聯絡方式，若聯絡不上則依序遞補。\n(二)若非本土語文教學支援人員，請勿報名。承辦學校將進行資格審查，資格符合者才能報名參加。\n(三)線上報名：\n七股潟湖及隆田chacha參訪活動線上報名系統\n(四)傳真報名人員請於115年6月18日(星期四)下班前傳真06-6622114，菁寮國小教導處報名。傳真後請電06-6621271#102，教導處林主任確認傳真報名是否成功。\n七、本活動請轉知貴校本土語文(閩語、客語、原民語)教學支援老師，參加人員所屬單位請給予公假登記。",
        "attachments": [
            {
                "name": "藝文場館參訪計畫-2(0519).pdf",
                "link": "https://www.cmjh.tn.edu.tw/modules/school/index.php?op=tufdl&fn=藝文場館參訪計畫-2(0519).pdf&files_sn=229"
            }
        ]
    },
    {
        "date": "2026-06-04",
        "category": "簡章",
        "source": "教務處",
        "title": "國立臺灣師範大學辦理「115學年度偏遠地區學士後教育學分班-童軍專長」",
        "url": "https://www.cmjh.tn.edu.tw/modules/school/index.php?department_id=2&zone_id=0&page_id=12&content_id=321&type=news&from_op=all_news",
        "content": "一、依據國立臺灣師範大學115年5月29日師大進字第1151014978號函辦理。\n二、檢附旨揭學分班招生簡章。",
        "attachments": [
            {
                "name": "修正後簡章.pdf",
                "link": "https://www.cmjh.tn.edu.tw/modules/school/index.php?op=tufdl&fn=修正後簡章.pdf&files_sn=228"
            }
        ]
    },
    {
        "date": "2026-06-04",
        "category": "研習",
        "source": "教務處",
        "title": "財團法人隆中向上教育基金會辦理「2026怪咖教育力系列活動」",
        "url": "https://www.cmjh.tn.edu.tw/modules/school/index.php?department_id=2&zone_id=0&page_id=12&content_id=320&type=news&from_op=all_news",
        "content": "一、依據財團法人隆中向上教育基金會115年5月27日隆教基字第1150527006號函辦理\n二、該會自108年啟動《怪咖計畫》，藉由橫跨性別平等、人權生命教育、環境生態及科技醫療社會等主題之「怪咖系列紀錄片」，融入社會議題思辨進入課程，響應素養導向教學。\n三、為鼓勵教育工作者以影像轉化議題教育，特別結合「SEL社會情緒學習」、「性別平等教育」、「環境教育」、「特殊教育輔導知能」等熱門關鍵字，舉辦一系列教育培力實體活動。\n四、活動摘要資訊如下：\n(一)邀請對象：各級學校教師、實習教師、師培生，以及對議題教育有興趣的教育工作者\n(二)活動地點：國立臺灣科學教育館（臺北市士林區士商路189號）\n(三)費用與報名：活動統一採網路報名，免費參加，名額有限，額滿為止。\n五、各級學校教師、實習老師、師培生、及對議題教育有興趣的教育工作者踴躍報名。\n六、活動相關事宜請恰本會電子信箱gx-foundation.org或電恰（04）2236-3910魏小姐\n七、檢附活動資訊1份供參。",
        "attachments": [
            {
                "name": "活動文宣.pdf",
                "link": "https://www.cmjh.tn.edu.tw/modules/school/index.php?op=tufdl&fn=活動文宣.pdf&files_sn=227"
            }
        ]
    },
    {
        "date": "2026-06-04",
        "category": "活動",
        "source": "學務處",
        "title": "國一升國二社團選社由此入",
        "url": "https://www.cmjh.tn.edu.tw/modules/school/index.php?department_id=3&zone_id=0&page_id=21&content_id=318&type=news&from_op=all_news",
        "content": "請一年級同學於6/10(三)下午6點前完成線上選社\n(1)社團一年一選（中途不可更換）\n(2)部分社團有收費或是訓練需求，請與家長確認可以接受再選\n(3)6/10下午6:00系統截止\n(4)同學可以利用下課時間或班會時間，完成線上選填作業後找副班長簽名！\n(5)有相關問題請洽學生活動組\n選填網址：\n一年級線上選社表單",
        "attachments": []
    },
    {
        "date": "2026-06-04",
        "category": "活動",
        "source": "學務處",
        "title": "國二升國三社團選社由此入",
        "url": "https://www.cmjh.tn.edu.tw/modules/school/index.php?department_id=3&zone_id=0&page_id=21&content_id=319&type=news&from_op=all_news",
        "content": "請二年級同學於6/10(三)晚上6點前完成社團選填\n(1)社團一年一選(中途不可更換)\n(2)部分社團有收費或訓練要求請與家長確認同意參加再選填\n(3)同學可利用下課或班會時間於班上完成選填後找副班長簽名\n(4)相關問題請洽學生活動組\n選填網址如下：\n二年級社團選填表單",
        "attachments": []
    },
    {
        "date": "2026-06-03",
        "category": "研習",
        "source": "教務處",
        "title": "「美感智能閱讀計畫-安妮新聞」115-1新進種子教師招募計畫，歡迎本校教師踴躍報名參加",
        "url": "https://www.cmjh.tn.edu.tw/modules/school/index.php?department_id=2&zone_id=0&page_id=12&content_id=317&type=news&from_op=all_news",
        "content": "說明：\n一、依據教育部115年5月29日臺教師(一)字第1150051533號函辦理。\n二、種子教師招募資訊：\n(一)招募對象：有意願於115-1學期使用美感智能閱讀刊物《安妮新聞》報紙於課堂中的國小、國中及高中職教師均可報名參與，不限學科及課程實施時數。\n(二)報名時間：115年6月1日（星期一）起至115年7月8日（星期三）止。\n(三)報名方式：線上填寫報名表單。\n(四)報名連結：\n《安妮新聞》種子教師報名表單連結\n。\n三、另辦理線上招募說明會：\n(一)活動時間：115年6月24日（星期三）下午1時30分至3時30分。\n(二)活動方式：活動前一週以e-mail提供Webex線上活動連結，會後提供影片檔。\n(三)報名方式：線上填寫種子教師報名表單，即日起至115年6月22日（星期一）止。\n四、本案相關事宜請洽聯絡人：國立成功大學計畫助理巫小姐，電話：06-2757575#50670，電子信箱critade@ncku.edu.tw。\n五、附上種子教師招募計畫書、申請辦法簡報及成果報告書各1份，請逕行下載參閱。",
        "attachments": [
            {
                "name": "成果報告書(閱讀推廣版).pdf",
                "link": "https://www.cmjh.tn.edu.tw/modules/school/index.php?op=tufdl&fn=成果報告書(閱讀推廣版).pdf&files_sn=223"
            },
            {
                "name": "成果報告書(原創設計與教案參考版).pdf",
                "link": "https://www.cmjh.tn.edu.tw/modules/school/index.php?op=tufdl&fn=成果報告書(原創設計與教案參考版).pdf&files_sn=224"
            },
            {
                "name": "種子教師招募計畫書.pdf",
                "link": "https://www.cmjh.tn.edu.tw/modules/school/index.php?op=tufdl&fn=種子教師招募計畫書.pdf&files_sn=225"
            },
            {
                "name": "申請辦法簡報.pdf",
                "link": "https://www.cmjh.tn.edu.tw/modules/school/index.php?op=tufdl&fn=申請辦法簡報.pdf&files_sn=226"
            }
        ]
    },
    {
        "date": "2026-06-03",
        "category": "活動",
        "source": "教務處",
        "title": "台南市115年度科學教育「校園生物多樣性暨蝴蝶養殖親子手作營」研習，請本校師生踴躍報名參加",
        "url": "https://www.cmjh.tn.edu.tw/modules/school/index.php?department_id=2&zone_id=0&page_id=12&content_id=316&type=news&from_op=all_news",
        "content": "說明：\n一、依據「臺南市115年度科學教育總體計畫」辦理。\n二、本活動重要資訊摘述如下：\n(一)時間及地點：115年8月22日 (六)09:00-14:30\n(二)參加對象：\n本市國中小自然領域教師(含代理代課教師)或對生物多樣性及蝴蝶養殖有興趣的親子。\n本計畫為親子探索營，計15組(親子 2 人 1組)共30人，額滿為止(因材料份數固定，已報名者請勿缺席)。不接受現場報名。\n(三)報名方式：自公告日起，請至\n科學教育總體計畫活動Google報名表單\n報名，依完成報名之先後順序錄取，額滿立即公告於\n新營國小學校網站\n，請上網確認是否報名成功，不接受現場報名。\n(四)檢附實施計畫詳如附件。\n(五)本案聯絡人：新營國小教務處陳意佳主任，06-6322136#111。",
        "attachments": [
            {
                "name": "「校園生物多樣性暨蝴蝶養殖親子手作營」實施計畫.pdf",
                "link": "https://www.cmjh.tn.edu.tw/modules/school/index.php?op=tufdl&fn=「校園生物多樣性暨蝴蝶養殖親子手作營」實施計畫.pdf&files_sn=222"
            }
        ]
    },
    {
        "date": "2026-06-03",
        "category": "升學",
        "source": "教務處",
        "title": "本校國三生報名五專聯免注意事項",
        "url": "https://www.cmjh.tn.edu.tw/modules/school/index.php?department_id=2&zone_id=0&page_id=12&content_id=314&type=news&from_op=all_news",
        "content": "報名日期：繳交資料至6/18(四)端午前截止，畢業後請自行主動至教務處註冊組繳交報名資料。\n取消報名：若因已錄取其他管道等原因取消報名，一樣在6/18(四)前攜帶已簽名(畢業生與家長)之放棄報名聲明書，至教務處放棄報名及退費。\n預計7/3寄發成績單及報到通知單，7/8現場登記分發。",
        "attachments": [
            {
                "name": "[放棄報名及退費] 聲明書.pdf",
                "link": "https://www.cmjh.tn.edu.tw/modules/school/index.php?op=tufdl&fn=[放棄報名及退費] 聲明書.pdf&files_sn=220"
            }
        ]
    },
    {
        "date": "2026-06-03",
        "category": "升學",
        "source": "教務處",
        "title": "116 學年度各直轄市、縣（市）就學區及共同就學區劃定結果一覽表",
        "url": "https://www.cmjh.tn.edu.tw/modules/school/index.php?department_id=2&zone_id=0&page_id=12&content_id=313&type=news&from_op=all_news",
        "content": "116學年度入學高中職之國二生適用。與今年畢業生相同。",
        "attachments": [
            {
                "name": "116 學年度各直轄市、縣（市）就學區及共同就學區劃定結果一覽表.pdf",
                "link": "https://www.cmjh.tn.edu.tw/modules/school/index.php?op=tufdl&fn=116 學年度各直轄市、縣（市）就學區及共同就學區劃定結果一覽表.pdf&files_sn=219"
            }
        ]
    },
    {
        "date": "2026-06-02",
        "category": "活動",
        "source": "輔導室",
        "title": "臺灣一滴優教育協會「選擇不卡關，未來不迷路：國升高未來導航講座」",
        "url": "https://www.cmjh.tn.edu.tw/modules/school/index.php?department_id=5&zone_id=0&page_id=39&content_id=273&type=news&from_op=all_news",
        "content": "臺灣一滴優教育協會「選擇不卡關，未來不迷路：國升高未來導航講座」\n說明：\n一、為協助學生瞭解108課綱下各類組之學習內容與發展方向，並釐清升學與職涯選擇之方向，本會辦理旨揭講座，邀請相關領域講者分享各類組特色與學習重點，協助學生探索自我興趣與未來藍圖。\n二、活動報名資訊如下：\n(一)時間：115年6月7日（星期日）19時00分至21時30分（18時45分開放入場）。\n(二)地點：Google Meet線上辦理。\n(三)參加對象：在學學生、教職員工及家長等有興趣者。\n(四)報名方式：請逕至Google表單填寫報名，報名連結：\n活動報名線上表單\n。\n三、檢附活動簡章1份於附件。\n四、如有未盡事宜，請洽本案活動承辦人陳筠峯，電子郵件：brianchen0807@edyouth.org",
        "attachments": [
            {
                "name": "選擇不卡關，未來不迷路：國升高未來導航講座.pdf",
                "link": "https://www.cmjh.tn.edu.tw/modules/school/index.php?op=tufdl&fn=選擇不卡關，未來不迷路：國升高未來導航講座.pdf&files_sn=218"
            }
        ]
    },
    {
        "date": "2026-06-02",
        "category": "研習",
        "source": "輔導室",
        "title": "南大附中「教師專業群科實作體驗活動」",
        "url": "https://www.cmjh.tn.edu.tw/modules/school/index.php?department_id=5&zone_id=0&page_id=39&content_id=272&type=news&from_op=all_news",
        "content": "南大附中「教師專業群科實作體驗活動」\n說明：\n一、依據114學年度高職優質化輔助方案子計畫:「114-3-2辦理國中教師專業群科實作體驗」辦理。\n二、辦理時間: 115年6月10日(星期三)下午1:30~4:30\n三、辦理項目及地點：\n1.食品製作實務-烘焙玩很大/本校食品加工科館\n2.畜產製作實務:從產地到餐桌-豬肉加工實作/本校畜產加工科館\n四、名額限制：\n1.食品製作實務-烘焙玩很大:20名。\n2.畜產製作實務:從產地到餐桌-豬肉加工實作:20名。\n如參與師長人數過多，將依照線上報名之先後順序錄取，如未獲錄取將另以e-mail通知。\n五、報名期限:即日起至115年6月9日下午4:00截止。\n六、報名連結：\n線上報名表單\n七、本校教師報名參加者請課務自理，予以公假登記。",
        "attachments": []
    },
    {
        "date": "2026-06-02",
        "category": "一般",
        "source": "總務處",
        "title": "公告標售本校奉准報廢之財物乙批，請踴躍參加投標，詳如附件。",
        "url": "https://www.cmjh.tn.edu.tw/modules/school/index.php?department_id=4&zone_id=0&page_id=30&content_id=271&type=news&from_op=all_news",
        "content": "",
        "attachments": [
            {
                "name": "115投標之標封.pdf",
                "link": "https://www.cmjh.tn.edu.tw/modules/school/index.php?op=tufdl&fn=115投標之標封.pdf&files_sn=212"
            },
            {
                "name": "115報廢明細表.pdf",
                "link": "https://www.cmjh.tn.edu.tw/modules/school/index.php?op=tufdl&fn=115報廢明細表.pdf&files_sn=213"
            },
            {
                "name": "115報廢財物投標單.pdf",
                "link": "https://www.cmjh.tn.edu.tw/modules/school/index.php?op=tufdl&fn=115報廢財物投標單.pdf&files_sn=214"
            },
            {
                "name": "115報廢財產投標須知.pdf",
                "link": "https://www.cmjh.tn.edu.tw/modules/school/index.php?op=tufdl&fn=115報廢財產投標須知.pdf&files_sn=215"
            },
            {
                "name": "1150602報廢公告.pdf",
                "link": "https://www.cmjh.tn.edu.tw/modules/school/index.php?op=tufdl&fn=1150602報廢公告.pdf&files_sn=216"
            }
        ]
    }
]